tokenring/__init__.py
tokenring/cli.py
tokenring/fidoclient.py
tokenring/handles.py
tokenring/interaction.py
tokenring/local.py
tokenring/vault.py
tokenring/agent/_admin_pipe.py
tokenring/agent/client.py
tokenring/agent/common.py
tokenring-2025.2.19.dist-info/METADATA
tokenring-2025.2.19.dist-info/WHEEL
tokenring-2025.2.19.dist-info/entry_points.txt
tokenring-2025.2.19.dist-info/top_level.txt
tokenring-2025.2.19.dist-info/RECORD
